metriql2tableau/__init__.py
metriql2tableau/boilerplate.tds
metriql2tableau/generate.py
metriql2tableau/metadata.py
metriql_tableau-0.7.data/scripts/metriql-tableau
metriql_tableau-0.7.dist-info/LICENSE
metriql_tableau-0.7.dist-info/METADATA
metriql_tableau-0.7.dist-info/WHEEL
metriql_tableau-0.7.dist-info/top_level.txt
metriql_tableau-0.7.dist-info/RECORD
