Metadata-Version: 2.1
Name: metriql-tableau
Version: 0.7
Summary: metriql Tableau integration
Home-page: https://github.com/metriql/metriql-tableau
Author: Burak Emre Kabakci
Author-email: emre@rakam.io
License: MIT License
Classifier: Development Status :: 3 - Alpha
Classifier: Intended Audience :: Developers
Classifier: License :: OSI Approved :: MIT License
Classifier: Operating System :: OS Independent
Classifier: Programming Language :: Python
Classifier: Programming Language :: Python :: 3 :: Only
Classifier: Programming Language :: Python :: 3.6
Classifier: Programming Language :: Python :: 3.7
Classifier: Topic :: Software Development :: Libraries
Classifier: Topic :: Software Development :: Libraries :: Python Modules
License-File: LICENSE
Requires-Dist: tableaudocumentapi (==0.9)
Provides-Extra: test
Requires-Dist: tableaudocumentapi (==0.9) ; extra == 'test'
